<?xml version="1.0" encoding="utf-8" ?>
<odoo>

    <record id="res_partner_inherit" model="ir.ui.view">
        <field name="name">Res Partner Inherit</field>
        <field name="model">res.partner</field>
        <field name="inherit_id" ref="base.view_partner_form"/>
        <field name="arch" type="xml">
            <xpath expr="//field[@name='vat']" position="after">
                <field name="message"/>
            </xpath>
            <xpath expr="//field[@name='vat']" position="before">
                <field name="other_informations"/>
            </xpath>
            <xpath expr="//field[@name='ref']" position="replace">
                <field name="message_2"/>
            </xpath>
        </field>
    </record>

    <record id="res_partner_tree_view_inherit" model="ir.ui.view">
        <field name="name">Res Partner Tree Inherit</field>
        <field name="model">res.partner</field>
        <field name="inherit_id" ref="base.view_partner_tree"/>
        <field name="arch" type="xml">
            <xpath expr="//field[@name='phone']" position="before">
                <field name="message"/>
            </xpath>
            <xpath expr="//field[@name='email']" position="after">
                <field name="other_informations"/>
            </xpath>
        </field>
    </record>
</odoo>
